amtproxy/__init__.py
amtproxy/config.py
amtproxy/dispatcher.py
amtproxy/exceptions.py
amtproxy/server.py
amtproxy/encryption/__init__.py
amtproxy/encryption/aes.py
amtproxy/encryption/crypto.py
amtproxy/protocols/__init__.py
amtproxy/protocols/real.py
amtproxy/protocols/telegram.py
aMTProxy-0.2.dist-info/LICENSE
aMTProxy-0.2.dist-info/METADATA
aMTProxy-0.2.dist-info/WHEEL
aMTProxy-0.2.dist-info/top_level.txt
aMTProxy-0.2.dist-info/RECORD
