Metadata-Version: 2.1
Name: aMTProxy
Version: 0.2
Summary: Async python MTProxy server
Home-page: https://github.com/Yurzs/pyMTProxy
Author: Yury (Yurzs)
Author-email: dev@best-service.online
License: UNKNOWN
Platform: UNKNOWN
Classifier: Programming Language :: Python :: 3
Classifier: License :: OSI Approved :: MIT License
Classifier: Operating System :: OS Independent
Requires-Dist: pyaes
